a2y_cppyy/__init__.py
a2y_cppyy-0.8.0.dist-info/LICENSE
a2y_cppyy-0.8.0.dist-info/METADATA
a2y_cppyy-0.8.0.dist-info/WHEEL
a2y_cppyy-0.8.0.dist-info/top_level.txt
a2y_cppyy-0.8.0.dist-info/RECORD
